pyTMHMM/TMHMM2.0.model
pyTMHMM/__init__.py
pyTMHMM/api.py
pyTMHMM/cli.py
pyTMHMM/hmm.cpython-311-darwin.so
pyTMHMM/hmm.pyx
pyTMHMM/model.py
pyTMHMM/utils.py
pyTMHMM-1.3.6.dist-info/LICENSE.md
pyTMHMM-1.3.6.dist-info/METADATA
pyTMHMM-1.3.6.dist-info/WHEEL
pyTMHMM-1.3.6.dist-info/entry_points.txt
pyTMHMM-1.3.6.dist-info/top_level.txt
pyTMHMM-1.3.6.dist-info/RECORD
