Metadata-Version: 2.1
Name: pyTMHMM
Version: 1.3.6
Summary: A transmembrane helix finder.
Home-page: https://github.com/bosborne/pyTMHMM/
Author: Brian Osborne
Author-email: bosborne@alum.mit.edu
License: MIT License
Classifier: Programming Language :: Python :: 3
Classifier: Topic :: Scientific/Engineering :: Bio-Informatics
Classifier: License :: OSI Approved :: MIT License
License-File: LICENSE.md
Requires-Dist: numpy (>=1.9)
Provides-Extra: plotting
Requires-Dist: matplotlib ; extra == 'plotting'
